.gitignore
CHANGES
LICENSE
cross_bdist_wininst.py
mkwin32.py
setup.py
upload-docs
amalgamation/libspatialite-amalgamation-3.0.1/AUTHORS
amalgamation/libspatialite-amalgamation-3.0.1/COPYING
amalgamation/libspatialite-amalgamation-3.0.1/INSTALL
amalgamation/libspatialite-amalgamation-3.0.1/Makefile.am
amalgamation/libspatialite-amalgamation-3.0.1/Makefile.in
amalgamation/libspatialite-amalgamation-3.0.1/README
amalgamation/libspatialite-amalgamation-3.0.1/aclocal.m4
amalgamation/libspatialite-amalgamation-3.0.1/config.guess
amalgamation/libspatialite-amalgamation-3.0.1/config.sub
amalgamation/libspatialite-amalgamation-3.0.1/configure
amalgamation/libspatialite-amalgamation-3.0.1/configure.ac
amalgamation/libspatialite-amalgamation-3.0.1/depcomp
amalgamation/libspatialite-amalgamation-3.0.1/install-sh
amalgamation/libspatialite-amalgamation-3.0.1/ltmain.sh
amalgamation/libspatialite-amalgamation-3.0.1/makefile.vc
amalgamation/libspatialite-amalgamation-3.0.1/missing
amalgamation/libspatialite-amalgamation-3.0.1/nmake.opt
amalgamation/libspatialite-amalgamation-3.0.1/spatialite.c
amalgamation/libspatialite-amalgamation-3.0.1/spatialite.pc.in
amalgamation/libspatialite-amalgamation-3.0.1/sqlite3.c
amalgamation/libspatialite-amalgamation-3.0.1/headers/Makefile.am
amalgamation/libspatialite-amalgamation-3.0.1/headers/Makefile.in
amalgamation/libspatialite-amalgamation-3.0.1/headers/spatialite.h
amalgamation/libspatialite-amalgamation-3.0.1/headers/spatialite/gaiaaux.h
amalgamation/libspatialite-amalgamation-3.0.1/headers/spatialite/gaiaexif.h
amalgamation/libspatialite-amalgamation-3.0.1/headers/spatialite/gaiageo.h
amalgamation/libspatialite-amalgamation-3.0.1/headers/spatialite/gg_advanced.h
amalgamation/libspatialite-amalgamation-3.0.1/headers/spatialite/gg_const.h
amalgamation/libspatialite-amalgamation-3.0.1/headers/spatialite/gg_core.h
amalgamation/libspatialite-amalgamation-3.0.1/headers/spatialite/gg_dynamic.h
lib/pyspatialite.egg-info/PKG-INFO
lib/pyspatialite.egg-info/SOURCES.txt
lib/pyspatialite.egg-info/dependency_links.txt
lib/pyspatialite.egg-info/top_level.txt
