Metadata-Version: 1.1
Name: pyspatialite
Version: 3.0.1-alpha-0
Summary: DB-API 2.0 interface for SQLite 3.x with Spatialite 3.0.1
Home-page: https://github.com/lokkju/pyspatialite/
Author: Lokkju Brennr
Author-email: lokkju@lokkju.com
License: zlib/libpng license
Platform: ALL
Classifier: Development Status :: 3 - Alpha
Classifier: Intended Audience :: Developers
Classifier: License :: OSI Approved :: zlib/libpng License
Classifier: Operating System :: MacOS :: MacOS X
Classifier: Operating System :: Microsoft :: Windows
Classifier: Operating System :: POSIX
Classifier: Programming Language :: C
Classifier: Programming Language :: Python
Classifier: Topic :: Database :: Database Engines/Servers
Classifier: Topic :: Software Development :: Libraries :: Python Modules
